my_lib/__init__.py
my_lib/dark_rrzex.py
dark_rrzex-0.0.1.dist-info/LICENSE
dark_rrzex-0.0.1.dist-info/METADATA
dark_rrzex-0.0.1.dist-info/WHEEL
dark_rrzex-0.0.1.dist-info/top_level.txt
dark_rrzex-0.0.1.dist-info/RECORD
