Metadata-Version: 2.1
Name: dark-rrzex
Version: 0.0.1
Summary: lib for ai
Home-page: https://github.com/A-X-1/test-lib
Author-email: alexcrow221@gmail.com
Classifier: Programming Language :: Python :: 3
Classifier: License :: OSI Approved :: MIT License
Classifier: Operating System :: OS Independent
Requires-Python: >=3.6
License-File: LICENSE
